Workbook

Sheet Leia-me
A1: PT 320 – Levantamento das bases para materialidade
A2: Suzano S.A. – demonstrações consolidadas – valores em R$ mil
A3: Preparado por: matrícula 241003769 – 20/10/2026 – trabalho acadêmico, não constitui opinião de auditoria
A5: Como usar
A6: 1. Aba "Bases": valores extraídos da DFP 2025 (texto em azul = dado de fonte; cada linha indica a página).
A7: 2. Aba "Comparação": faixas de materialidade para cada base. Os percentuais mínimo e máximo (azul) podem ser alterados.
A8: 3. Aba "Simulador": escolha a base e os percentuais nas células amarelas; a planilha calcula materialidade global, para execução e limite de distorção trivial.
A9: 4. Aba "Fontes": documentos, endereços e páginas.
A11: Convenção de cores
A12: Azul = dado de entrada ou fonte · Preto = fórmula · Verde = link para outra aba · Fundo amarelo = escolha do preparador
A14: Referência normativa
A15: NBC TA 320 (R1), itens A4–A8: referenciais possíveis (lucro antes do imposto, receita, lucro bruto, despesas, patrimônio líquido, ativos);
A16: lucro volátil pode justificar outro referencial ou lucro normalizado (A5–A6); exemplo de 5% do lucro antes do imposto para manufatura (A8).

Sheet Bases
A1: Base (consolidado, R$ mil) | B1: 2023 | C1: 2024 | D1: 2025 | E1: Fonte / página | F1: Observação
A2: Receita líquida | B2: 39755575 | C2: 47403282 | D2: 50115679 | E2: F1 p. 30 – DRE, conta 3.01
A3: Lucro (prejuízo) antes dos tributos sobre o lucro | B3: 17997216 | C3: -13111053 | D3: 20411174 | E3: F1 p. 30 – DRE, conta 3.07 | F3: Prejuízo em 2024 causado pelo resultado financeiro (câmbio e derivativos)
A4: Resultado financeiro | B4: 5780928 | C4: -28802145 | D4: 9762165 | E4: F1 p. 30 – DRE, conta 3.06 | F4: Explica a volatilidade do lucro
A5: Lucro (prejuízo) líquido consolidado | B5: 14106381 | C5: -7044706 | D5: 13437687 | E5: F1 p. 30 – DRE, conta 3.11
A6: Resultado bruto | B6: 14678900 | C6: 20001755 | D6: 16226175 | E6: F1 p. 30 – DRE, conta 3.03
A7: EBITDA ajustado | C7: 23849000 | D7: 21736000 | E7: F1 p. 44–45 – Relatório da Administração | F7: Medida gerencial, não auditada; divulgada em R$ milhões (convertida)
A8: Ativo total | B8: 143593025 | C8: 165936105 | D8: 167935519 | E8: F1 p. 25 – BP, conta 1
A9: Patrimônio líquido consolidado | B9: 44810300 | C9: 32415575 | D9: 43952173 | E9: F1 p. 28 – BP, conta 2.03
A10: Imobilizado (nota 15) | C10: 64986040 | D10: 64296187 | E10: F2 p. 70 – BP; nota 15 | F10: Conta da base simulada – só para comparação
A11: Lucro antes dos tributos normalizado (média 2023–2025) | D11: =AVERAGE(B3:D3) -> 8432445.7 | E11: Cálculo – NBC TA 320, A6 | F11: Média simples dos 3 anos, para neutralizar a oscilação do resultado financeiro
A13: Valores em R$ mil. Texto azul = dado copiado da fonte. EBITDA ajustado: R$ 21.736 milhões (2025) e R$ 23.849 milhões (2024); 2023 não consta na DFP 2025.

Sheet Comparação
A1: Base | B1: Valor 2025 | C1: Variação 2024→2025 | D1: Oscilação 2023–2025 (desvio/média) | E1: % mínimo | F1: % máximo | G1: Materialidade mínima | H1: Materialidade máxima | I1: Mat. máxima em % do lucro antes dos tributos 2025 | J1: A favor | K1: Contra
A2: Lucro antes dos tributos 2025 | B2: =Bases!D3 -> 20411174 | C2: =IFERROR((Bases!D3-Bases!C3)/ABS(Bases!C3),"n.a.") -> 2.5567914 | D2: =IFERROR(STDEV(Bases!B3:D3)/ABS(AVERAGE(Bases!B3:D3)),"n.a.") -> 2.2171762 | E2: 0.03 | F2: 0.05 | G2: =B2*E2 -> 612335.22 | H2: =B2*F2 -> 1020558.7 | I2: =H2/Bases!$D$3 -> 0.05 | J2: Referencial mais usado para entidades com fins lucrativos (A5); 5% é o exemplo da norma para manufatura (A8) | K2: Muito volátil: prejuízo de R$ 13,1 bi em 2024 e lucro de R$ 20,4 bi em 2025, por câmbio e derivativos
A3: Lucro antes dos tributos normalizado (média 3 anos) | B3: =Bases!D11 -> 8432445.7 | C3: n.a. | D3: n.a. | E3: 0.03 | F3: 0.05 | G3: =B3*E3 -> 252973.37 | H3: =B3*F3 -> 421622.28 | I3: =H3/Bases!$D$3 -> 0.020656445 | J3: Atenua a volatilidade, como prevê a norma (A6); mantém o foco no resultado | K3: Média depende do período escolhido; mistura um ano de prejuízo
A4: Receita líquida | B4: =Bases!D2 -> 50115679 | C4: =IFERROR((Bases!D2-Bases!C2)/ABS(Bases!C2),"n.a.") -> 0.057219603 | D4: =IFERROR(STDEV(Bases!B2:D2)/ABS(AVERAGE(Bases!B2:D2)),"n.a.") -> 0.11740858 | E4: 0.005 | F4: 0.01 | G4: =B4*E4 -> 250578.4 | H4: =B4*F4 -> 501156.79 | I4: =H4/Bases!$D$3 -> 0.02455306 | J4: Estável e crescente; recomendada quando o lucro é volátil (A5); usuários acompanham volume e preço da celulose | K4: Não reflete a rentabilidade; pode gerar materialidade alta em relação ao lucro
A5: EBITDA ajustado | B5: =Bases!D7 -> 21736000 | C5: =IFERROR((Bases!D7-Bases!C7)/ABS(Bases!C7),"n.a.") -> -0.088599103 | D5: =IFERROR(STDEV(Bases!B7:D7)/ABS(AVERAGE(Bases!B7:D7)),"n.a.") -> 0.065552995 | E5: 0.01 | F5: 0.02 | G5: =B5*E5 -> 217360 | H5: =B5*F5 -> 434720 | I5: =H5/Bases!$D$3 -> 0.021298138 | J5: Indicador acompanhado pelo mercado e usado em cláusulas de dívida (dívida líquida/EBITDA) | K5: Medida gerencial, não auditada e definida pela própria Companhia
A6: Ativo total | B6: =Bases!D8 -> 167935519 | C6: =IFERROR((Bases!D8-Bases!C8)/ABS(Bases!C8),"n.a.") -> 0.012049301 | D6: =IFERROR(STDEV(Bases!B8:D8)/ABS(AVERAGE(Bases!B8:D8)),"n.a.") -> 0.084910949 | E6: 0.005 | F6: 0.01 | G6: =B6*E6 -> 839677.59 | H6: =B6*F6 -> 1679355.2 | I6: =H6/Bases!$D$3 -> 0.082276266 | J6: Empresa intensiva em capital (imobilizado e florestas); base estável | K6: Gera os maiores valores; menos usada para companhias abertas com foco em resultado
A7: Patrimônio líquido | B7: =Bases!D9 -> 43952173 | C7: =IFERROR((Bases!D9-Bases!C9)/ABS(Bases!C9),"n.a.") -> 0.35589676 | D7: =IFERROR(STDEV(Bases!B9:D9)/ABS(AVERAGE(Bases!B9:D9)),"n.a.") -> 0.17135998 | E7: 0.01 | F7: 0.02 | G7: =B7*E7 -> 439521.73 | H7: =B7*F7 -> 879043.46 | I7: =H7/Bases!$D$3 -> 0.043066776 | J7: Relevante para acionistas | K7: Oscilou com o prejuízo de 2024 (R$ 32,4 bi para R$ 44,0 bi)
A9: Leitura: "Oscilação" = desvio-padrão dos 3 anos dividido pela média; quanto maior, menos estável a base (NBC TA 320, A4(e)).
A11: Faixas percentuais: referências usuais de mercado, ajustáveis (azul). A norma cita 5% do lucro antes do imposto como exemplo para manufatura (A8).
A13: A coluna I mostra quanto a materialidade representaria do lucro antes dos tributos de 2025 – ajuda a avaliar se o valor é razoável para o usuário.
A15: EBITDA ajustado, oscilação: calculada só com 2024 e 2025. Variação 2024→2025 do lucro usa o valor absoluto de 2024 (prejuízo).

Sheet Simulador
A1: Simulador de materialidade (preencha as células amarelas)
A3: Base escolhida | B3: Receita líquida | D3: Selecione na lista
A4: Valor da base (R$ mil) | B4: =INDEX(Comparação!B2:B7,MATCH(B3,Comparação!A2:A7,0)) -> 50115679 | D4: Puxado da aba Comparação
A5: % aplicado | B5: 0.005 | D5: Julgamento do preparador
A6: Materialidade global (R$ mil) | B6: =B4*B5 -> 250578.4 | D6: NBC TA 320, item 10
A7: % para materialidade de execução | B7: 0.5 | D7: Prática de mercado: 50% a 75% da global, conforme o risco; a norma não fixa percentual (item 11)
A8: Materialidade para execução (R$ mil) | B8: =B6*B7 -> 125289.2 | D8: NBC TA 320, item 11
A9: % para limite de distorção claramente trivial | B9: 0.05 | D9: Prática de mercado: 3% a 5% da global; a norma não fixa percentual (NBC TA 450, A2)
A10: Limite de distorção claramente trivial (R$ mil) | B10: =B6*B9 -> 12528.92 | D10: Abaixo disso, a distorção não é acumulada
A12: Para comparação
A13: Materialidade global em % do ativo total | B13: =B6/Bases!D8 -> 0.0014921108
A14: Materialidade global em % do lucro antes dos tributos 2025 | B14: =B6/Bases!D3 -> 0.01227653
A15: Materialidade global em % do imobilizado | B15: =B6/Bases!D10 -> 0.0038972512 | D15: Conta da base simulada (PT 530)
A17: Escolha do preparador (20/10/2026): receita líquida, 0,5% (global) e 50% (execução) – fundamentação no PT 320.

Sheet Fontes
A1: Ref. | B1: Documento | C1: Endereço eletrônico | D1: Data de acesso | E1: Páginas
A2: F1 | B2: DFP 31/12/2025, versão 1 – Suzano S.A. (demonstrações individuais e consolidadas) | C2: https://www.rad.cvm.gov.br/ENETWEB/frmGerenciaPaginaFRE.aspx?NumeroSequencialDocumento=154674&CodigoTipoInstituicao=1 | D2: 46314 | E2: p. 25, 28, 30, 44–45
A3: F2 | B3: Demonstrações financeiras 2025 – site de RI da Suzano | C3: https://ri.suzano.com.br/Portuguese/Informacoes-Financeiras/Central-de-Resultados/default.aspx | D3: 46314 | E3: p. 70 (balanço; nota 15)
A4: F3 | B4: NBC TA 320 (R1) – Materialidade no planejamento e na execução da auditoria | C4: https://www1.cfc.org.br/sisweb/sre/detalhes_sre.aspx?codigo=2016/NBCTA320(R1) | D4: 46315 | E4: Itens 10–11, A4–A8
